{"date":"2025-01-05","departure_time":"09:00 AM","origin":"CM House, Ranchi, Jharkhand","destination":"Harmu Chowk, Ranchi, Jharkhand","realtime_min":8.8,"freeflow_time":7.3,"traffic_delay_min":1.5,"delay_percent":20.8,"distance_km":3.8,"traffic_condition":"游릭","origin_lat":23.3441,"origin_lng":85.3096,"destination_lat":23.3574,"destination_lng":85.3158}
{"date":"2025-01-05","departure_time":"09:00 AM","origin":"Harmu Chowk, Ranchi, Jharkhand","destination":"CM House, Ranchi, Jharkhand","realtime_min":9.5,"freeflow_time":6.1,"traffic_delay_min":3.4,"delay_percent":55.5,"distance_km":3.8,"traffic_condition":"游리","origin_lat":23.3574,"origin_lng":85.3158,"destination_lat":23.3441,"destination_lng":85.3096}
{"date":"2025-01-05","departure_time":"09:00 AM","origin":"Harmu Chowk, Ranchi, Jharkhand","destination":"HEC Gate, Ranchi, Jharkhand","realtime_min":14.9,"freeflow_time":13.2,"traffic_delay_min":1.7,"delay_percent":12.8,"distance_km":8.7,"traffic_condition":"游릭","origin_lat":23.3574,"origin_lng":85.3158,"destination_lat":23.4013,"destination_lng":85.2785}
{"date":"2025-01-05","departure_time":"09:00 AM","origin":"HEC Gate, Ranchi, Jharkhand","destination":"Harmu Chowk, Ranchi, Jharkhand","realtime_min":16.4,"freeflow_time":13.5,"traffic_delay_min":2.9,"delay_percent":21.1,"distance_km":8.7,"traffic_condition":"游릭","origin_lat":23.4013,"origin_lng":85.2785,"destination_lat":23.3574,"destination_lng":85.3158}
{"date":"2025-01-05","departure_time":"09:00 AM","origin":"Radium Road, Ranchi, Jharkhand","destination":"Albertekka Chowk, Ranchi, Jharkhand","realtime_min":3.3,"freeflow_time":2.5,"traffic_delay_min":0.8,"delay_percent":30.7,"distance_km":1.4,"traffic_condition":"游리","origin_lat":23.3716,"origin_lng":85.3251,"destination_lat":23.3746,"destination_lng":85.3278}
{"date":"2025-01-05","departure_time":"09:00 AM","origin":"Albertekka Chowk, Ranchi, Jharkhand","destination":"Rajendra Chowk, Ranchi, Jharkhand","realtime_min":7.4,"freeflow_time":5.9,"traffic_delay_min":1.5,"delay_percent":25.1,"distance_km":3.0,"traffic_condition":"游리","origin_lat":23.3746,"origin_lng":85.3278,"destination_lat":23.3789,"destination_lng":85.3182}
{"date":"2025-01-05","departure_time":"09:00 AM","origin":"Rajbhawan Chowk, Ranchi, Jharkhand","destination":"Booty More Chowk, Ranchi, Jharkhand","realtime_min":20.6,"freeflow_time":13.6,"traffic_delay_min":7.0,"delay_percent":51.2,"distance_km":6.8,"traffic_condition":"游리","origin_lat":23.3818,"origin_lng":85.3185,"destination_lat":23.4125,"destination_lng":85.3063}
{"date":"2025-01-05","departure_time":"09:00 AM","origin":"Mecon Chowk, Ranchi, Jharkhand","destination":"Airport, Ranchi, Jharkhand","realtime_min":17.0,"freeflow_time":14.2,"traffic_delay_min":2.8,"delay_percent":19.7,"distance_km":7.6,"traffic_condition":"游릭","origin_lat":23.3439,"origin_lng":85.2874,"destination_lat":23.3145,"destination_lng":85.3216}
